{
  "pairs": [
    {
      "names": [
        "param_12",
        "param_3"
      ],
      "bw": 0.17105925499422414
    },
    {
      "names": [
        "param_10",
        "param_7"
      ],
      "bw": 0.20176034295541306
    },
    {
      "names": [
        "param_4",
        "param_8"
      ],
      "bw": 0.20176034295541306
    },
    {
      "names": [
        "param_11",
        "param_9"
      ],
      "bw": 0.1575077619622975
    },
    {
      "names": [
        "param_0",
        "param_1"
      ],
      "bw": 0.1857766776356282
    },
    {
      "names": [
        "param_2",
        "param_5"
      ],
      "bw": 0.1857766776356282
    }
  ],
  "singles": [
    {
      "name": "param_6",
      "bw": 0.050513496101483014
    }
  ]
}