{"data_mtime": 1719052711, "dep_lines": [74, 75, 76, 79, 81, 73, 77, 78, 55, 56, 57, 58, 59, 71, 1, 1, 1, 1, 1, 1, 1, 1, 1, 1, 1, 1, 1, 1, 1, 1, 1, 1, 1, 1, 1, 1, 1, 1, 62, 66, 67, 61, 349], "dep_prios": [5, 5, 5, 5, 5, 5, 5, 5, 5, 5, 10, 10, 5, 5, 5, 20, 20, 30, 30, 30, 30, 30, 30, 30, 30, 30, 30, 30, 30, 30, 30, 30, 30, 30, 30, 30, 30, 30, 5, 5, 5, 5, 20], "dependencies": ["sqlalchemy.engine.base", "sqlalchemy.ext.declarative", "sqlalchemy.ext.mutable", "sqlalchemy.sql.schema", "camcops_server.cc_modules.cc_cache", "sqlalchemy.engine", "sqlalchemy.orm", "sqlalchemy.schema", "abc", "io", "logging", "sqlite3", "typing", "pendulum", "builtins", "pyexpat.errors", "pyexpat.model", "_typeshed", "array", "ctypes", "datetime", "mmap", "pendulum.date", "pendulum.datetime", "pendulum.mixins", "pendulum.mixins.default", "pickle", "sqlalchemy", "sqlalchemy.engine.interfaces", "sqlalchemy.ext", "sqlalchemy.log", "sqlalchemy.sql", "sqlalchemy.sql.base", "sqlalchemy.sql.ddl", "sqlalchemy.sql.elements", "sqlalchemy.sql.selectable", "sqlalchemy.sql.visitors", "sqlite3.dbapi2"], "hash": "a0d0842c59752f9ee9c3d43c177e6038cc9d46099ea1e3cc0b2328d506f901fc", "id": "camcops_server.cc_modules.cc_sqlalchemy", "ignore_all": true, "interface_hash": "54d76b5a04cc15aaa5d47705adbf6076e5b1d0cab2c671aad5d62dfd88e6042e", "mtime": 1719050179, "options": {"allow_redefinition": false, "allow_untyped_globals": false, "always_false": [], "always_true": [], "bazel": false, "check_untyped_defs": false, "disable_error_code": [], "disabled_error_codes": [], "disallow_any_decorated": false, "disallow_any_explicit": false, "disallow_any_expr": false, "disallow_any_generics": false, "disallow_any_unimported": false, "disallow_incomplete_defs": false, "disallow_subclassing_any": false, "disallow_untyped_calls": false, "disallow_untyped_decorators": false, "disallow_untyped_defs": false, "enable_error_code": [], "enabled_error_codes": [], "follow_imports": "normal", "follow_imports_for_stubs": false, "ignore_errors": false, "ignore_missing_imports": false, "implicit_reexport": true, "local_partial_types": false, "mypyc": false, "no_implicit_optional": false, "platform": "linux", "plugins": [], "show_none_errors": true, "strict_concatenate": false, "strict_equality": false, "strict_optional": true, "strict_optional_whitelist": null, "warn_no_return": true, "warn_return_any": false, "warn_unreachable": false, "warn_unused_ignores": false}, "path": "/home/martinb/workspace/camcops/server/camcops_server/cc_modules/cc_sqlalchemy.py", "plugin_data": null, "size": 13714, "suppressed": ["cardinal_pythonlib.sqlalchemy.dialect", "cardinal_pythonlib.sqlalchemy.dump", "cardinal_pythonlib.sqlalchemy.session", "cardinal_pythonlib.logs", "pymysql.converters"], "version_id": "0.982"}